MANIFEST.in
README.rst
setup.py
auth_additions/VERSION
auth_additions/__init__.py
auth_additions/__init__.pyc
auth_additions/admin.py
auth_additions/admin.pyc
auth_additions/backends.py
auth_additions/backends.pyc
auth_additions/context_processors.py
auth_additions/forms.py
auth_additions/forms.pyc
auth_additions/middleware.py
auth_additions/models.py
auth_additions/models.pyc
auth_additions/urls.py
auth_additions/views.py
auth_additions/management/__init__.py
auth_additions/management/__init__.pyc
auth_additions/management/commands/__init__.py
auth_additions/management/commands/freshen_permissions.py
auth_additions/migrations/0001_add_column_group_rank.py
auth_additions/migrations/0001_add_column_group_rank.pyc
auth_additions/migrations/0002_increase_column_lengths.py
auth_additions/migrations/0002_increase_column_lengths.pyc
auth_additions/migrations/0003_increase_permission_name_length.py
auth_additions/migrations/0003_increase_permission_name_length.pyc
auth_additions/migrations/__init__.py
auth_additions/migrations/__init__.pyc
auth_additions/templates/admin/auth/duplicate_group.html
django_auth_additions.egg-info/PKG-INFO
django_auth_additions.egg-info/SOURCES.txt
django_auth_additions.egg-info/dependency_links.txt
django_auth_additions.egg-info/top_level.txt