Metadata-Version: 1.0
Name: django-auth-additions
Version: 0.6.2
Summary: Additions (monkey-patches) to auth models.
Home-page: http://bitbucket.org/schinckel/django-auth-additions
Author: Matthew Schinckel
Author-email: matt@schinckel.net
License: UNKNOWN
Platform: UNKNOWN
Classifier: Programming Language :: Python
Classifier: License :: OSI Approved :: BSD License
Classifier: Operating System :: OS Independent
Classifier: Framework :: Django
